Workbook

Sheet 汇总
A1: V6 SWP
B2: 该科目涉及OSP底稿可参考此链接 | D2: OSP K1 SWP 固定资产及在建工程盘点 202YMMDD XYZ公司.xlsx
B4: J.00 | C4: J.00 Lead Sheet（认定：E, C） | F4: 程序页 | G4: 执行 | H4: 不执行的原因
B5: 1 | C5: 获取和编制在建工程两期变动的引导表，并与试算平衡表和上年底稿核对一致。对在建工程变动建立预期并说明理由，对不符合预期的变动以及异常变动进行调查和分析。 | F5: J.00 Lead sheet | G5: 是
B6: J.01 | C6: J.01 Agree SL to GL（认定：BS：E、V、C IS：M、C） | F6: 程序页 | G6: 执行 | H6: 不执行的原因
B7: 1 | C7: 我们获取了本年在建工程明细清单，该清单包含在建工程的变动，并将金额与试算表进行核对。 | F7: J.01 Agree SL to GL | G7: 是
B8: J.02.1 | C8: J.02.1 CIP additions(TOD)（认定：BS：E、V、C、R&O、P&D IS：M、P&D） | F8: 程序页 | G8: 执行 | H8: 不执行的原因
B9: 1 | C9: 获取在建工程新增清单，并将列表与在建工程后推核对一致。调差超过SAD名义金额的差异。 | F9: J.02.1 CIP additions(TOD) | G9: 是
B10: 2 | C10: 对于本期新增的建工程项目，将大于测试阈值或存在重大错报风险的项目作为关键项（key item）,我们使用安永抽样工具选择代表性样本，将抽取的样本查看相关支持文件。 | G10: 是
B11: J.02.2 | C11: J.02.2 CIP transfer (TOD)（认定：BS：E、V、C、R&O、P&D IS：M、P&D） | F11: 程序页 | G11: 执行 | H11: 不执行的原因
B12: 1 | C12: 获取在建工程转出清单，并将列表与固定资产后推核对一致。调差超过SAD名义金额的差异。 | F12: J.02.2 CIP transfer (TOD) | G12: 是
B13: 2 | C13: 对于本期转出的建工程项目，将大于测试阈值或存在重大错报风险的项目作为关键项（key item）,我们使用安永抽样工具选择代表性样本，将抽取的样本查看相关支持文件。 | G13: 是
B14: 3 | C14: 本年转出的在建工程金额与其他科目转入的在建工程金额进行核对，并对差异进行检查。 | G14: 是
B15: J.03 | C15: J.03 CIP长期挂账（认定：BS：E、V、C、R&O、P&D IS：M、P&D） | F15: 程序页 | G15: 执行 | H15: 不执行的原因
B16: 1 | C16: 对于余额重大长期挂账的在建工程，我们考虑其合理性。 | F16: J.03 CIP长期挂账 | G16: 否 | H16: 期初无余额，期末余额为预付定制软件款项，已调整。
B17: 2 | C17: 我们将期末在建工程清单（如项目清单）作为总体，选取金额重大且长期挂账的在建工程作为样本。 | G17: 否 | H17: 期初无余额，期末余额为预付定制软件款项，已调整。
B18: J.04 | C18: J.04 资产的减值（认定：BS: V IS: M） | F18: 程序页 | G18: 执行 | H18: 不执行的原因
B19: 1 | C19: 1.使用在审计过程中所获得的信息来确定管理层是否已识别适当的减值迹象；可使用PSP Canvas form K.04: 识别减值迹象，也可使用 <SWP减值迹象识别> 对减值迹象进行评估，并根据指引要求获取相关支持性文件。 2.如有减值迹象的，评价管理层假设、未来现金流等减值评估的合理性，核实并测算减值金额。 3.检查是否存在转回在建工程减值准备的情况，确定减值准备在以后会计期间没有转回。 | G19: 否 | H19: 期初无余额，期末余额为预付定制软件款项，已调整。

Sheet SkywindSettingSheet
A1: 4e8a7199-876e-4a55-b346-7babaa25151c
