Workbook

Sheet 汇总
A1: V6 SWP
B2: 该科目涉及OSP底稿及函证底稿可参考此链接 | F2: OSP N SWP 应付账款账龄复核 202YMMDD XYZ公司.xlsx
F3: 函证 SWP 负债类科目 202YMMDD XYZ公司.xlsx
B5: N.00 | C5: N.00 应付账款引导表（认定：E、C） | F5: 程序页 | G5: 执行 | H5: 不执行的原因 | I5: 注意事项
B6: 1 | C6: 我们将两期金额进行比对，对那些变动大于范围或异常的事项，获得管理层解释并对解释是否合理进行调查并获取相关的支持性文件。 | F6: N.00 Lead sheet
B7: 2 | C7: 如果项目仅对部分总账科目执行程序，需评估未执行程序的总账科目加总金额是否大于TE，如大于TE，请项目组执行额外的测试程序。
B8: N.01 | C8: N.01 将明细账与总账核对一致（认定：E、C、V） | F8: 程序页 | G8: 执行 | H8: 不执行的原因 | I8: 注意事项
B9: 1 | C9: 获取应付账款明细账（列示至各供应商的余额）N.01.01明细账BKD，与总账核对，如差异大于SAD，获取差异差异调节表并对调节项金额大于测试阈值及性质异常的项目执行进一步测试。 | F9: N.01 明细账与总账核对
B10: 2 | C10: 对应付账款外币余额，我们使用第三方汇率(独立于被审计单位获得汇率)重新计算，并将重新计算的余额与被审计单位的余额进行比较。
B11: N.02 | C11: N.02 异常项复核（认定：E、C、V、R&O、P&D） | F11: 程序页 | G11: 执行 | H11: 不执行的原因 | I11: 注意事项
B12: 1 | C12: 对（单独或合计）大于测试阈值的借方余额，获取记账分录并检查对应支持性文件，确定对方科目账务处理是否正确，应付账款借方余额是否有必要根据名义金额进行重分类调整。 | F12: N.02 异常项复核
B13: 2 | C13: 根据应付账款明细账，我们识别金额、供应商或其他被认为异常或预期外的项目（例如，关联方、员工、客户、严重逾期余额），选择项目并记录做出此决定的依据；我们获取这些项目的支持性证据并记录检查结果。
B14: N.03 | C14: N.03 应付账款截止测试（认定：E、C、R&O） | F14: 程序页 | G14: 执行 | H14: 不执行的原因 | I14: 注意事项
B15: 1 | C15: 若我们从其他程序中获得一部分审计证据（交叉索引至相关底稿）或未获取审计证据时，需结合我们对于被审计单位业务的了解，考虑截止性测试的范围与涵盖期间，基于风险评估确定样本策略，并记录我们认为影响我们确定截止时间、样本策略的因素。 IPE 考虑： | F15: N.03 截止测试 | I15: 若我们已从其他程序中获得了充分适当的审计证据，以应对应付账款截止风险时，无需执行本程序，并交叉索引至相关底稿；
B16: N.04 | C16: N.04寻找未入账负债（认定：C、V） | F16: 程序页 | G16: 执行 | H16: 不执行的原因 | I16: 注意事项
B17: 1 | C17: 通过寻找未入账的应付账款，验证资产负债表日应付账款的计价和完整性。 | F17: N.04 寻找未入账负债

Sheet N.00 Lead sheet
B1: 标准工作底稿: N SWP 应付账款
B2: 客户名称 | C2: 东风鸿远工程咨询有限公司 | D2: 此工作底稿需要与以下 Canvas PSP guided workflow forms一起使用： •N.00应付账款引导表 •N.01将明细账与总账核对一致 •N.02异常项复核 •N.03应付账款截止测试 •N.04寻找未入账负债 •账户结论
B3: 期末 | C3: 46387
B4: 分析日期 | C4: 46170.668
B5: 可容忍误差（TE）
B6: 名义金额（SAD）
B7: 适用会计准则 | C7: PRC
B8: 记账本位币 | C8: CNY
B9: N.00 编制引导表并比较余额
B11: 返回汇总页
D13: Threshold(s) | H13: 安永标记
B14: 认定 | C14: CRA | D14: 各项认定1 | E14: 所有相关认定 2 | H14: TB | I14: 已与科目余额表核对无误
B15: 完整性 (C) | D15: =IF(C15="Minimal",$C$5*50%,IF(C15="Low",$C$5*25%,IF(C15="Moderate",$C$5*15%,IF(C15="High",$C$5*10%,IF(C15="N/A","-",))))) | E15: =MIN($D$15:$D$19) | H15: PY | I15: 与上年最终审定数核对一致
B16: 存在性 (E) | D16: =IF(C16="Minimal",$C$5*100%,IF(C16="Low",$C$5*75%,IF(C16="Moderate",$C$5*50%,IF(C16="High",$C$5*25%,IF(C16="N/A","-",))))) | H16: A3 | I16: 与未审数、审定数核对一致
B17: 计价（V） | D17: =IF(C17="Minimal",$C$5*100%,IF(C17="Low",$C$5*75%,IF(C17="Moderate",$C$5*50%,IF(C17="High",$C$5*25%,IF(C17="N/A","-",))))) | H17: A5 | I17: 与审计调整核对一致
B18: 权利和义务（R&O） | D18: =IF(C18="Minimal",$C$5*100%,IF(C18="Low",$C$5*75%,IF(C18="Moderate",$C$5*50%,IF(C18="High",$C$5*25%,IF(C18="N/A","-",))))) | H18: FS | I18: 与FS.0x与财务报表核对无误
B19: 列报和披露（P&D） | D19: =IF(C19="Minimal",$C$5*100%,IF(C19="Low",$C$5*75%,IF(C19="Moderate",$C$5*50%,IF(C19="High",$C$5*25%,IF(C19="N/A","-",))))) | H19: w | I19: 低于SAD的金额——放弃进一步调查
B20: 1 各项认定的测试阈值，是根据EY GAM SUBSTANTIVE DESIGN 2.2.1 | H20: Rx | I20: 重新计算，无异常
B21: 中的示例测试阈值（用占TE的百分比表示）在相应风险等级（CRA）区间的上限计算得出的。 | H21: m | I21: 余额/活动不符合测试范围–无需进一步调查
B22: 除负债/费用类别账户的完整性认定应当使用负债/费用账户表之外，其他类别账户和认定均可使用资产/收入账户表。 | H22: SL | I22: 已与明细账核对无误
B23: 2 所有相关认定的测试阈值，是所有有效认定对应之测试阈值的最小值。我们在 Lead中使用该测试阈值：（a）作为选取总账账户进行测试的起点；（b）作为（需要进一步调查的）金额波动范围的起点。
B25: 在下文中描述我们对应付账款在此期间的相关账户余额和相关波动的预期，以及我们对这些预期的依据和理由。
B30: 波动范围
B31: ="波动幅度 ("&C8& "):" | C31: =$E$15
B32: 波动幅度 (%): | C32: 0.1
F35: |------- TB -------| | K35: |------- PY -------|
B36: 表1 | F36: ="货币/单位: "&C8
B37: 账套名称/账套编码 | C37: 总账科目编码 | D37: 科目名称 | E37: 索引号 | F37: =C3 | K37: =DATE(YEAR($C$3)-1,12,31) | L37: 本期和上期期末余额 | N37: Notes | O37: 基于波动幅度判断，是否进一步调查？ | P37: 基于定性考虑判断，是否进一步调查？
F38: 期末账面数 | G38: 账表调整数 | H38: 期末未审数 | I38: 审计调整数 | J38: 期末审定数 | K38: 上期末审定数 | L38: 变动金额 | M38: 变动%
B39: 东风鸿远工程咨询有限公司 | C39: 2121 | D39: 应付账款 | E39: N.01/ | H39: =F39+G39 | J39: =H39+I39 | K39: -57526376 | L39: =J39-K39 | M39: =IFERROR(L39/K39,1) | N39: [A] | O39: =IF(AND(ABS(L39)>=$C$31,ABS(M39)>=$C$32),"是","否")
H40: =F40+G40 | J40: =H40+I40 | K40: 0 | L40: =J40-K40 | M40: =IFERROR(L40/K40,1) | O40: =IF(AND(ABS(L40)>=$C$31,ABS(M40)>=$C$32),"是","否")
H41: =F41+G41 | J41: =H41+I41 | L41: =J41-K41 | M41: =IFERROR(L41/K41,1) | O41: =IF(AND(ABS(L41)>=$C$31,ABS(M41)>=$C$32),"是","否")
H42: =F42+G42 | J42: =H42+I42 | L42: =J42-K42 | M42: =IFERROR(L42/K42,1) | O42: =IF(AND(ABS(L42)>=$C$31,ABS(M42)>=$C$32),"是","否")
H43: =F43+G43 | J43: =H43+I43 | L43: =J43-K43 | M43: =IFERROR(L43/K43,1) | O43: =IF(AND(ABS(L43)>=$C$31,ABS(M43)>=$C$32),"是","否")
D46: 合计 | F46: =SUM(F39:F43) | G46: =SUM(G39:G43) | H46: =SUM(H39:H43) | I46: =SUM(I39:I43) | J46: =SUM(J39:J43) | K46: =SUM(K39:K43) | L46: =J46-K46 | M46: =IFERROR(L46/K46,1) | O46: =IF(AND(ABS(L46)>=$C$31,ABS(M46)>=$C$32),"是","否")
F47: RX | G47: RX | H47: RX | I47: RX | J47: RX | K47: RX
G48: A3
G49: Diff | H49: =H46-H48 | J49: =J46-J48 | K49: =K46-K48
E50: 未执行程序的总账科目加总金额是否大于TE | F50: =IF(ABS(F45-'N.01 明细账与总账核对'!E18)>'N.00 Lead sheet'!$C$5,"是","否") | G50: Note2
B52: 波动说明
B53: [A]
B59: Note2：如果项目仅对部分总账科目执行程序，需评估未执行程序的总账科目加总金额是否大于TE，如大于TE，请项目组执行额外的测试程序。(如不适用请删除）
B66: 表2 应付账款周转率分析
D67: =C3 | E67: =K37 | F67: 变动%
E68: PY
B69: 应付账款平均余额 a | D69: =(J46+K46)/2 | E69: -60856881 | F69: =IFERROR((D69-E69)/E69,"")
B70: 销售成本 b | C70: /UGP_Lead | E70: 64381069 | F70: =IFERROR((D70-E70)/E70,"")
B72: 周转天数 c=a/b*365 | D72: =IFERROR(ABS(D69)/ABS(D70)*365,0) | E72: 345.02008 | F72: =IFERROR((D72-E72)/E72,"")
B73: 周转率 d=b/a | D73: =IFERROR(ABS(D70)/ABS(D69),0) | E73: 1.0579095 | F73: =IFERROR((D73-E73)/E73,"")
B75: 分析:
B76: 在此输入分析。
B79: 调整汇总表（如不适用请删除）
B80: 调整类型

Sheet N.01 明细账与总账核对
B1: 标准工作底稿: N SWP 应付账款
B2: N.01: 明细账与总账核对并执行细节测试
B4: 返回汇总页
B6: =MIN('N.00 Lead sheet'!$D$15,'N.00 Lead sheet'!$D$16) | C6: 用于识别总账和明细账之间差异的测试阈值
B9: 表1 将明细账与总账核对一致。 | I9: |------- Rx -------|
B10: 账套名称/账套编码 | C10: 总账科目编码 | D10: 科目名称 | E10: Lead页余额 | F10: 索引号 | G10: 明细账余额 | H10: 明细账索引 | I10: 差异重新计算 （Note1） | J10: 外币余额
J11: 是否适当重新计量? (使用下拉列表) | K11: 工作底稿参考
E12: =-IFERROR(_xlfn.XLOOKUP(C12,'N.00 Lead sheet'!$C$39:$C$43,'N.00 Lead sheet'!$F$39:$F$43),0) | F12: /N.00 | H12: /N.01.01明细账 | I12: =E12-G12 | K12: =IF(J12="","",IF(J12="是","Note2",IF(J12="否","Note2","不适用")))
E13: =-IFERROR(_xlfn.XLOOKUP(C13,'N.00 Lead sheet'!$C$39:$C$43,'N.00 Lead sheet'!$F$39:$F$43),0) | I13: =E13-G13 | K13: =IF(J13="","",IF(J13="是","Note2",IF(J13="否","Note2","不适用")))
E14: =-IFERROR(_xlfn.XLOOKUP(C14,'N.00 Lead sheet'!$C$39:$C$43,'N.00 Lead sheet'!$F$39:$F$43),0) | I14: =E14-G14 | K14: =IF(J14="","",IF(J14="是","Note2",IF(J14="否","Note2","不适用")))
E15: =-IFERROR(_xlfn.XLOOKUP(C15,'N.00 Lead sheet'!$C$39:$C$43,'N.00 Lead sheet'!$F$39:$F$43),0) | I15: =E15-G15 | K15: =IF(J15="","",IF(J15="是","Note2",IF(J15="否","Note2","不适用")))
E16: =-IFERROR(_xlfn.XLOOKUP(C16,'N.00 Lead sheet'!$C$39:$C$43,'N.00 Lead sheet'!$F$39:$F$43),0) | I16: =E16-G16 | K16: =IF(J16="","",IF(J16="是","Note2",IF(J16="否","Note2","不适用")))
D18: 合计 | E18: =SUM(E12:E16) | G18: =SUM(G12:G16) | I18: =SUM(I12:I16)
E19: RX | G19: RX | I19: RX
B21: Note1：如果总账和明细账差异金额大于SAD请在以下解释差异并执行相应的程序：针对金额大于测试阈值及性质异常的项目我们需进一步进行测试。(如不适用请删除）
B26: Note2：对外币余额，我们使用第三方汇率（独立于客户获得汇率）重新计算，并将重新计算的余额与客户的余额进行比较。(如不适用请删除）
C27: |------- N.01.01明细账 -------| | D27: EY Works | F27: |------- N.01.01明细账 -------|
B28: 原币币种 | C28: 原币金额 | D28: 折算汇率 | E28: 折合本位币 | F28: 账面本位币金额 | G28: 差异
B29: USD | E29: =C29*D29 | G29: =E29-F29
B30: CNY | E30: =C30*D30 | G30: =E30-F30
E31: =C31*D31 | G31: =E31-F31

Sheet N.01.01明细账
B1: 标准底稿: N SWP 应付账款
B2: N.01.01 获取应付账款明细账
B5: 账套名称/账套编码 | C5: 科目编码 | D5: 供应商代码 | E5: 供应商名称 | F5: 款项性质 | G5: 供应商性质 | H5: 46387 | N5: 46022 | O5: 变动 | Q5: Notes | R5: 应付账款分账龄
H6: 原币币种 | I6: 原币金额 | J6: 期末账面数 | K6: 本期审计调整编号 | L6: 重分类调整 | M6: 期末审定数 | N6: 上期末审定数 | O6: 金额 | P6: % | R6: 0-90天 | S6: 91-365天 | T6: 1年至2年 | U6: 2年至3年 | V6: 3年以上 | W6: check
B7: 东风鸿远工程咨询有限公司 | C7: 2121 | D7: I_9202 | E7: 东风鸿远工程咨询有限公司监理分公司 | F7: 采购款 | G7: 关联方 | H7: CNY | M7: =J7+L7 | N7: 0 | O7: =M7-N7 | P7: =IF(N7<>0,O7/N7,"") | W7: =SUM(R7:V7)-M7 | X7: =T7+U7+V7
B8: 东风鸿远工程咨询有限公司 | C8: 2121 | D8: I_9149 | E8: 东风咨询有限公司 | F8: 采购款 | G8: 关联方 | H8: CNY | M8: =J8+L8 | N8: -3874030.1 | O8: =M8-N8 | P8: =IF(N8<>0,O8/N8,"") | Q8: NB1 | W8: =SUM(R8:V8)-M8 | X8: =T8+U8+V8
B9: 东风鸿远工程咨询有限公司 | C9: 2121 | D9: I_9151 | E9: 东风国际招标有限公司 | F9: 采购款 | G9: 关联方 | H9: CNY | M9: =J9+L9 | N9: -24168.87 | O9: =M9-N9 | P9: =IF(N9<>0,O9/N9,"") | W9: =SUM(R9:V9)-M9 | X9: =T9+U9+V9
B10: 东风鸿远工程咨询有限公司 | C10: 2121 | D10: I_9201 | E10: 东风鸿远工程咨询有限公司武汉分公司 | F10: 采购款 | G10: 关联方 | H10: CNY | M10: =J10+L10 | N10: 0 | O10: =M10-N10 | P10: =IF(N10<>0,O10/N10,"") | W10: =SUM(R10:V10)-M10 | X10: =T10+U10+V10
B11: 东风鸿远工程咨询有限公司 | C11: 2121 | D11: I_9205 | E11: 上海东南联合工程设计有限公司武汉分公司 | F11: 采购款 | G11: 关联方 | H11: CNY | M11: =J11+L11 | N11: -321415.1 | O11: =M11-N11 | P11: =IF(N11<>0,O11/N11,"") | W11: =SUM(R11:V11)-M11 | X11: =T11+U11+V11
B12: 东风鸿远工程咨询有限公司 | C12: 2121 | D12: I_9204 | E12: 上海东南联合工程设计有限公司 | F12: 采购款 | G12: 关联方 | H12: CNY | M12: =J12+L12 | N12: -188000 | O12: =M12-N12 | P12: =IF(N12<>0,O12/N12,"") | W12: =SUM(R12:V12)-M12 | X12: =T12+U12+V12
B13: 东风鸿远工程咨询有限公司 | C13: 2121 | D13: I_2446 | E13: 联友智连科技有限公司 | F13: 采购款 | G13: 关联方 | H13: CNY | M13: =J13+L13 | N13: -9744.98 | O13: =M13-N13 | P13: =IF(N13<>0,O13/N13,"") | W13: =SUM(R13:V13)-M13 | X13: =T13+U13+V13
B14: 东风鸿远工程咨询有限公司 | C14: 2121 | D14: E_614092 | E14: 襄阳市市政工程设计院有限公司 | F14: 采购款 | G14: 供应商 | H14: CNY | M14: =J14+L14 | N14: -1101157.4 | O14: =M14-N14 | P14: =IF(N14<>0,O14/N14,"") | W14: =SUM(R14:V14)-M14 | X14: =T14+U14+V14
B15: 东风鸿远工程咨询有限公司 | C15: 2121 | D15: E_625077 | E15: 中城科泽工程设计集团有限责任公司襄阳分院 | F15: 采购款 | G15: 供应商 | H15: CNY | M15: =J15+L15 | N15: -19417.48 | O15: =M15-N15 | P15: =IF(N15<>0,O15/N15,"") | W15: =SUM(R15:V15)-M15 | X15: =T15+U15+V15
B16: 东风鸿远工程咨询有限公司 | C16: 2121 | D16: E_624605 | E16: 湖北王壹建筑装饰工程有限公司 | F16: 采购款 | G16: 供应商 | H16: CNY | M16: =J16+L16 | N16: 0 | O16: =M16-N16 | P16: =IF(N16<>0,O16/N16,"") | W16: =SUM(R16:V16)-M16 | X16: =T16+U16+V16
B17: 东风鸿远工程咨询有限公司 | C17: 2121 | D17: E_624955 | E17: 襄阳瑞喜钻探工程有限公司 | F17: 采购款 | G17: 供应商 | H17: CNY | M17: =J17+L17 | N17: -937233.68 | O17: =M17-N17 | P17: =IF(N17<>0,O17/N17,"") | W17: =SUM(R17:V17)-M17 | X17: =T17+U17+V17
B18: 东风鸿远工程咨询有限公司 | C18: 2121 | D18: E_175725 | E18: 中机三勘岩土工程有限公司 | F18: 采购款 | G18: 供应商 | H18: CNY | M18: =J18+L18 | N18: -2565700 | O18: =M18-N18 | P18: =IF(N18<>0,O18/N18,"") | Q18: NB6 | W18: =SUM(R18:V18)-M18 | X18: =T18+U18+V18
B19: 东风鸿远工程咨询有限公司 | C19: 2121 | D19: E_622567 | E19: 湖北省地源洁能工程有限公司 | F19: 采购款 | G19: 供应商 | H19: CNY | M19: =J19+L19 | N19: 0 | O19: =M19-N19 | P19: =IF(N19<>0,O19/N19,"") | W19: =SUM(R19:V19)-M19 | X19: =T19+U19+V19
B20: 东风鸿远工程咨询有限公司 | C20: 2121 | D20: E_612717 | E20: 湖北建研立科低碳科技有限公司 | F20: 采购款 | G20: 供应商 | H20: CNY | M20: =J20+L20 | N20: -230500 | O20: =M20-N20 | P20: =IF(N20<>0,O20/N20,"") | W20: =SUM(R20:V20)-M20 | X20: =T20+U20+V20
B21: 东风鸿远工程咨询有限公司 | C21: 2121 | D21: E_679403 | E21: 襄阳汇达讯财务咨询有限公司 | F21: 采购款 | G21: 供应商 | H21: CNY | M21: =J21+L21 | N21: -16693.76 | O21: =M21-N21 | P21: =IF(N21<>0,O21/N21,"") | W21: =SUM(R21:V21)-M21 | X21: =T21+U21+V21
B22: 东风鸿远工程咨询有限公司 | C22: 2121 | D22: 66666 | E22: 虚拟客商 | F22: 采购款 | G22: 供应商 | H22: CNY | M22: =J22+L22 | N22: 0 | O22: =M22-N22 | P22: =IF(N22<>0,O22/N22,"") | W22: =SUM(R22:V22)-M22 | X22: =T22+U22+V22
B23: 东风鸿远工程咨询有限公司 | C23: 2121 | D23: E_622929 | E23: 武汉管陈岩土工程有限公司 | F23: 采购款 | G23: 供应商 | H23: CNY | M23: =J23+L23 | N23: -15125.25 | O23: =M23-N23 | P23: =IF(N23<>0,O23/N23,"") | W23: =SUM(R23:V23)-M23 | X23: =T23+U23+V23
B24: 东风鸿远工程咨询有限公司 | C24: 2121 | D24: E_580949 | E24: 中建三局集团有限公司 | F24: 采购款 | G24: 供应商 | H24: CNY | M24: =J24+L24 | N24: -1857538.5 | O24: =M24-N24 | P24: =IF(N24<>0,O24/N24,"") | W24: =SUM(R24:V24)-M24 | X24: =T24+U24+V24
B25: 东风鸿远工程咨询有限公司 | C25: 2121 | D25: E_622215 | E25: 山东庆辉联达地质勘察有限公司 | F25: 采购款 | G25: 供应商 | H25: CNY | M25: =J25+L25 | N25: -100602 | O25: =M25-N25 | P25: =IF(N25<>0,O25/N25,"") | W25: =SUM(R25:V25)-M25 | X25: =T25+U25+V25
B26: 东风鸿远工程咨询有限公司 | C26: 2121 | D26: E_614445 | E26: 湖北襄拓建工程有限公司 | F26: 采购款 | G26: 供应商 | H26: CNY | M26: =J26+L26 | N26: -380988.56 | O26: =M26-N26 | P26: =IF(N26<>0,O26/N26,"") | W26: =SUM(R26:V26)-M26 | X26: =T26+U26+V26
B27: 东风鸿远工程咨询有限公司 | C27: 2121 | D27: E_598238 | E27: 中信建筑设计研究总院有限公司 | F27: 采购款 | G27: 供应商 | H27: CNY | M27: =J27+L27 | N27: -124711.5 | O27: =M27-N27 | P27: =IF(N27<>0,O27/N27,"") | W27: =SUM(R27:V27)-M27 | X27: =T27+U27+V27
B28: 东风鸿远工程咨询有限公司 | C28: 2121 | D28: E_601843 | E28: 中国建筑设计研究院有限公司 | F28: 采购款 | G28: 供应商 | H28: CNY | M28: =J28+L28 | N28: 0 | O28: =M28-N28 | P28: =IF(N28<>0,O28/N28,"") | W28: =SUM(R28:V28)-M28 | X28: =T28+U28+V28
B29: 东风鸿远工程咨询有限公司 | C29: 2121 | D29: E_612459 | E29: 武汉狮山风景园林规划设计有限公司 | F29: 采购款 | G29: 供应商 | H29: CNY | M29: =J29+L29 | N29: -1073083.3 | O29: =M29-N29 | P29: =IF(N29<>0,O29/N29,"") | W29: =SUM(R29:V29)-M29 | X29: =T29+U29+V29
B30: 东风鸿远工程咨询有限公司 | C30: 2121 | D30: E_608358 | E30: 新泰市泉沟镇华中钻井队 | F30: 采购款 | G30: 供应商 | H30: CNY | M30: =J30+L30 | N30: -43649.5 | O30: =M30-N30 | P30: =IF(N30<>0,O30/N30,"") | W30: =SUM(R30:V30)-M30 | X30: =T30+U30+V30
B31: 东风鸿远工程咨询有限公司 | C31: 2121 | D31: E_468464 | E31: 湖北建科国际工程有限公司 | F31: 采购款 | G31: 供应商 | H31: CNY | M31: =J31+L31 | N31: -33909.5 | O31: =M31-N31 | P31: =IF(N31<>0,O31/N31,"") | W31: =SUM(R31:V31)-M31 | X31: =T31+U31+V31
B32: 东风鸿远工程咨询有限公司 | C32: 2121 | D32: E_625163 | E32: 老河口市蕴航工程勘察有限公司 | F32: 采购款 | G32: 供应商 | H32: CNY | M32: =J32+L32 | N32: -269573.72 | O32: =M32-N32 | P32: =IF(N32<>0,O32/N32,"") | W32: =SUM(R32:V32)-M32 | X32: =T32+U32+V32
B33: 东风鸿远工程咨询有限公司 | C33: 2121 | D33: E_623952 | E33: 武汉蕃华施工图设计审查有限公司 | F33: 采购款 | G33: 供应商 | H33: CNY | M33: =J33+L33 | N33: -3883.5 | O33: =M33-N33 | P33: =IF(N33<>0,O33/N33,"") | W33: =SUM(R33:V33)-M33 | X33: =T33+U33+V33
B34: 东风鸿远工程咨询有限公司 | C34: 2121 | D34: E_683167 | E34: 武汉企创通企业服务有限公司 | F34: 采购款 | G34: 供应商 | H34: CNY | M34: =J34+L34 | N34: -3564.36 | O34: =M34-N34 | P34: =IF(N34<>0,O34/N34,"") | W34: =SUM(R34:V34)-M34 | X34: =T34+U34+V34
... B48: 东风鸿远工程咨询有限公司 | C48: 2121 | D48: E_624681 | E48: 湖北南诚工程咨询有限公司 | F48: 采购款 | G48: 供应商 | H48: CNY | M48: =J48+L48 | N48: -70000 | O48: =M48-N48 | P48: =IF(N48<>0,O48/N48,"") | W48: =SUM(R48:V48)-M48 | X48: =T48+U48+V48
B49: 东风鸿远工程咨询有限公司 | C49: 2121 | D49: E_605958 | E49: 四川省建筑设计研究院有限公司 | F49: 采购款 | G49: 供应商 | H49: CNY | M49: =J49+L49 | N49: -6146733.9 | O49: =M49-N49 | P49: =IF(N49<>0,O49/N49,"") | Q49: NB7 | W49: =SUM(R49:V49)-M49 | X49: =T49+U49+V49
B50: 东风鸿远工程咨询有限公司 | C50: 2121 | D50: E_622843 | E50: 武汉游途网络科技有限公司 | F50: 采购款 | G50: 供应商 | H50: CNY | M50: =J50+L50 | N50: 0 | O50: =M50-N50 | P50: =IF(N50<>0,O50/N50,"") | W50: =SUM(R50:V50)-M50 | X50: =T50+U50+V50
B51: 东风鸿远工程咨询有限公司 | C51: 2121 | D51: E_618178 | E51: 北京盈建科软件股份有限公司 | F51: 采购款 | G51: 供应商 | H51: CNY | M51: =J51+L51 | N51: -40000 | O51: =M51-N51 | P51: =IF(N51<>0,O51/N51,"") | W51: =SUM(R51:V51)-M51 | X51: =T51+U51+V51
B52: 东风鸿远工程咨询有限公司 | C52: 2121 | D52: E_613804 | E52: 武汉意创格致建筑工程设计有限公司 | F52: 采购款 | G52: 供应商 | H52: CNY | M52: =J52+L52 | N52: -15637.12 | O52: =M52-N52 | P52: =IF(N52<>0,O52/N52,"") | W52: =SUM(R52:V52)-M52 | X52: =T52+U52+V52
B53: 东风鸿远工程咨询有限公司 | C53: 2121 | D53: E_614043 | E53: 汉江中保信保安服务集团有限公司 | F53: 采购款 | G53: 供应商 | H53: CNY | M53: =J53+L53 | N53: -33300 | O53: =M53-N53 | P53: =IF(N53<>0,O53/N53,"") | W53: =SUM(R53:V53)-M53 | X53: =T53+U53+V53
B54: 东风鸿远工程咨询有限公司 | C54: 2121 | D54: E_619093 | E54: 中兵北勘(河北)工程检测有限公司 | F54: 采购款 | G54: 供应商 | H54: CNY | M54: =J54+L54 | N54: 0 | O54: =M54-N54 | P54: =IF(N54<>0,O54/N54,"") | W54: =SUM(R54:V54)-M54 | X54: =T54+U54+V54
B55: 东风鸿远工程咨询有限公司 | C55: 2121 | D55: E_600087 | E55: 湖北省鄂西北工程勘察有限责任公司 | F55: 采购款 | G55: 供应商 | H55: CNY | M55: =J55+L55 | N55: -2189774.6 | O55: =M55-N55 | P55: =IF(N55<>0,O55/N55,"") | Q55: NB8 | W55: =SUM(R55:V55)-M55 | X55: =T55+U55+V55
B56: 东风鸿远工程咨询有限公司 | C56: 2121 | D56: E_602726 | E56: 临海市华意建筑设计有限公司 | F56: 采购款 | G56: 供应商 | H56: CNY | M56: =J56+L56 | N56: -28155.34 | O56: =M56-N56 | P56: =IF(N56<>0,O56/N56,"") | W56: =SUM(R56:V56)-M56 | X56: =T56+U56+V56
B57: 东风鸿远工程咨询有限公司 | C57: 2121 | D57: E_614472 | E57: 湖北襄阳松涛建筑工程有限公司 | F57: 采购款 | G57: 供应商 | H57: CNY | M57: =J57+L57 | N57: -216627.45 | O57: =M57-N57 | P57: =IF(N57<>0,O57/N57,"") | W57: =SUM(R57:V57)-M57 | X57: =T57+U57+V57
B58: 东风鸿远工程咨询有限公司 | C58: 2121 | D58: E_659776 | E58: 湖北永勘地质勘查技术有限公司 | F58: 采购款 | G58: 供应商 | H58: CNY | M58: =J58+L58 | N58: -914.6 | O58: =M58-N58 | P58: =IF(N58<>0,O58/N58,"") | W58: =SUM(R58:V58)-M58 | X58: =T58+U58+V58
B59: 东风鸿远工程咨询有限公司 | C59: 2121 | D59: E_614267 | E59: 湖北禾汇工程造价咨询有限公司 | F59: 采购款 | G59: 供应商 | H59: CNY | M59: =J59+L59 | N59: -1588352.2 | O59: =M59-N59 | P59: =IF(N59<>0,O59/N59,"") | W59: =SUM(R59:V59)-M59 | X59: =T59+U59+V59
B60: 东风鸿远工程咨询有限公司 | C60: 2121 | D60: E_602949 | E60: 亿企赢企业服务（广州）有限公司 | F60: 采购款 | G60: 供应商 | H60: CNY | M60: =J60+L60 | N60: -157102.52 | O60: =M60-N60 | P60: =IF(N60<>0,O60/N60,"") | W60: =SUM(R60:V60)-M60 | X60: =T60+U60+V60
B61: 东风鸿远工程咨询有限公司 | C61: 2121 | D61: E_227041 | E61: 中核勘察设计研究有限公司 | F61: 采购款 | G61: 供应商 | H61: CNY | M61: =J61+L61 | N61: -319104.37 | O61: =M61-N61 | P61: =IF(N61<>0,O61/N61,"") | W61: =SUM(R61:V61)-M61 | X61: =T61+U61+V61
B62: 东风鸿远工程咨询有限公司 | C62: 2121 | D62: E_614102 | E62: 湖北伟利德商贸有限公司 | F62: 采购款 | G62: 供应商 | H62: CNY | M62: =J62+L62 | N62: -13365 | O62: =M62-N62 | P62: =IF(N62<>0,O62/N62,"") | W62: =SUM(R62:V62)-M62 | X62: =T62+U62+V62
B63: 东风鸿远工程咨询有限公司 | C63: 2121 | D63: E_613334 | E63: 武汉汇沐家居有限公司 | F63: 采购款 | G63: 供应商 | H63: CNY | M63: =J63+L63 | N63: -25767.17 | O63: =M63-N63 | P63: =IF(N63<>0,O63/N63,"") | W63: =SUM(R63:V63)-M63 | X63: =T63+U63+V63
B64: 东风鸿远工程咨询有限公司 | C64: 2121 | D64: E_629280 | E64: 武汉鸿利源岩土工程劳务有限公司 | F64: 采购款 | G64: 供应商 | H64: CNY | M64: =J64+L64 | N64: -92679.61 | O64: =M64-N64 | P64: =IF(N64<>0,O64/N64,"") | W64: =SUM(R64:V64)-M64 | X64: =T64+U64+V64
B65: 东风鸿远工程咨询有限公司 | C65: 2121 | D65: E_613970 | E65: 襄阳君和盛建筑装饰设计工程有限公司 | F65: 采购款 | G65: 供应商 | H65: CNY | M65: =J65+L65 | N65: -1030997.9 | O65: =M65-N65 | P65: =IF(N65<>0,O65/N65,"") | W65: =SUM(R65:V65)-M65 | X65: =T65+U65+V65
B66: 东风鸿远工程咨询有限公司 | C66: 2121 | D66: E_659630 | E66: 武汉炽炫数字科技有限公司 | F66: 采购款 | G66: 供应商 | H66: CNY | M66: =J66+L66 | N66: -78178.22 | O66: =M66-N66 | P66: =IF(N66<>0,O66/N66,"") | W66: =SUM(R66:V66)-M66 | X66: =T66+U66+V66
B67: 东风鸿远工程咨询有限公司 | C67: 2121 | D67: E_614419 | E67: 襄阳市城市规划设计院有限公司 | F67: 采购款 | G67: 供应商 | H67: CNY | M67: =J67+L67 | N67: -2130188.7 | O67: =M67-N67 | P67: =IF(N67<>0,O67/N67,"") | W67: =SUM(R67:V67)-M67 | X67: =T67+U67+V67
... B94: 东风鸿远工程咨询有限公司 | C94: 2121 | D94: E_668731 | E94: 武汉江城建设咨询有限公司谷城分公司 | F94: 采购款 | G94: 供应商 | H94: CNY | M94: =J94+L94 | N94: -27766.99 | O94: =M94-N94 | P94: =IF(N94<>0,O94/N94,"") | W94: =SUM(R94:V94)-M94 | X94: =T94+U94+V94
B95: 东风鸿远工程咨询有限公司 | C95: 2121 | D95: E_628682 | E95: 供应商 | F95: 采购款 | G95: 供应商 | H95: CNY | M95: =J95+L95 | N95: -2743396.2 | O95: =M95-N95 | P95: =IF(N95<>0,O95/N95,"") | Q95: NB2 | W95: =SUM(R95:V95)-M95 | X95: =T95+U95+V95
B96: 东风鸿远工程咨询有限公司 | C96: 2121 | D96: E_614845 | E96: 随州市宜鸿机电有限公司 | F96: 采购款 | G96: 供应商 | H96: CNY | M96: =J96+L96 | N96: -16941.74 | O96: =M96-N96 | P96: =IF(N96<>0,O96/N96,"") | W96: =SUM(R96:V96)-M96 | X96: =T96+U96+V96
B97: 东风鸿远工程咨询有限公司 | C97: 2121 | D97: E_624410 | E97: 襄阳市永通广告传播有限公司 | F97: 采购款 | G97: 供应商 | H97: CNY | M97: =J97+L97 | N97: -16504.85 | O97: =M97-N97 | P97: =IF(N97<>0,O97/N97,"") | W97: =SUM(R97:V97)-M97 | X97: =T97+U97+V97
B98: 东风鸿远工程咨询有限公司 | C98: 2121 | D98: E_598233 | E98: 中南建筑设计院股份有限公司 | F98: 采购款 | G98: 供应商 | H98: CNY | M98: =J98+L98 | N98: -603784.91 | O98: =M98-N98 | P98: =IF(N98<>0,O98/N98,"") | W98: =SUM(R98:V98)-M98 | X98: =T98+U98+V98
B99: 东风鸿远工程咨询有限公司 | C99: 2121 | D99: E_614260 | E99: 襄阳市金枫叶装饰设计工程有限公司 | F99: 采购款 | G99: 供应商 | H99: CNY | M99: =J99+L99 | N99: -1053032.3 | O99: =M99-N99 | P99: =IF(N99<>0,O99/N99,"") | W99: =SUM(R99:V99)-M99 | X99: =T99+U99+V99
B100: 东风鸿远工程咨询有限公司 | C100: 2121 | D100: E_622115 | E100: 城安工程技术集团有限公司 | F100: 采购款 | G100: 供应商 | H100: CNY | M100: =J100+L100 | N100: -317036.99 | O100: =M100-N100 | P100: =IF(N100<>0,O100/N100,"") | W100: =SUM(R100:V100)-M100 | X100: =T100+U100+V100
B101: 东风鸿远工程咨询有限公司 | C101: 2121 | D101: E_596969 | E101: 三峡大学 | F101: 采购款 | G101: 供应商 | H101: CNY | M101: =J101+L101 | N101: -75471.7 | O101: =M101-N101 | P101: =IF(N101<>0,O101/N101,"") | W101: =SUM(R101:V101)-M101 | X101: =T101+U101+V101
B102: 东风鸿远工程咨询有限公司 | C102: 2121 | D102: E_216546 | E102: 湖北志明电子科技有限公司 | F102: 采购款 | G102: 供应商 | H102: CNY | M102: =J102+L102 | N102: -17287.55 | O102: =M102-N102 | P102: =IF(N102<>0,O102/N102,"") | W102: =SUM(R102:V102)-M102 | X102: =T102+U102+V102
B103: 东风鸿远工程咨询有限公司 | C103: 2121 | D103: E_623582 | E103: 武汉固地鼎兴工程技术有限公司 | F103: 采购款 | G103: 供应商 | H103: CNY | M103: =J103+L103 | N103: -0.5 | O103: =M103-N103 | P103: =IF(N103<>0,O103/N103,"") | W103: =SUM(R103:V103)-M103 | X103: =T103+U103+V103
B104: 东风鸿远工程咨询有限公司 | C104: 2121 | D104: E_614195 | E104: 襄阳园冶风景园林集团有限公司 | F104: 采购款 | G104: 供应商 | H104: CNY | M104: =J104+L104 | N104: -340862.27 | O104: =M104-N104 | P104: =IF(N104<>0,O104/N104,"") | W104: =SUM(R104:V104)-M104 | X104: =T104+U104+V104
B105: 东风鸿远工程咨询有限公司 | C105: 2121 | D105: E_013569 | E105: 华诚博远工程技术集团有限公司 | F105: 采购款 | G105: 供应商 | H105: CNY | M105: =J105+L105 | N105: -2830.19 | O105: =M105-N105 | P105: =IF(N105<>0,O105/N105,"") | W105: =SUM(R105:V105)-M105 | X105: =T105+U105+V105
B106: 东风鸿远工程咨询有限公司 | C106: 2121 | D106: E_725139 | E106: 程晓明 | F106: 采购款 | G106: 供应商 | H106: CNY | M106: =J106+L106 | N106: -9600 | O106: =M106-N106 | P106: =IF(N106<>0,O106/N106,"") | W106: =SUM(R106:V106)-M106 | X106: =T106+U106+V106
B107: 东风鸿远工程咨询有限公司 | C107: 2121 | D107: E_466380 | E107: 襄阳富思特建设工程质量检测有限公司 | F107: 采购款 | G107: 供应商 | H107: CNY | M107: =J107+L107 | N107: -406000 | O107: =M107-N107 | P107: =IF(N107<>0,O107/N107,"") | W107: =SUM(R107:V107)-M107 | X107: =T107+U107+V107
... B163: 东风鸿远工程咨询有限公司 | C163: 2121 | D163: E_607898 | E163: 武汉峰境俪致园林景观工程设计有限公司 | F163: 采购款 | G163: 供应商 | H163: CNY | M163: =J163+L163 | N163: -271844.66 | O163: =M163-N163 | P163: =IF(N163<>0,O163/N163,"") | W163: =SUM(R163:V163)-M163 | X163: =T163+U163+V163
B164: 东风鸿远工程咨询有限公司 | C164: 2121 | D164: E_177287 | E164: 襄阳诚智电力设计有限公司 | F164: 采购款 | G164: 供应商 | H164: CNY | M164: =J164+L164 | N164: -1160377.4 | O164: =M164-N164 | P164: =IF(N164<>0,O164/N164,"") | Q164: NB3 | W164: =SUM(R164:V164)-M164 | X164: =T164+U164+V164
B165: 东风鸿远工程咨询有限公司 | C165: 2121 | D165: E_599650 | E165: 清华大学建筑设计研究院有限公司 | F165: 采购款 | G165: 供应商 | H165: CNY | M165: =J165+L165 | N165: -174528.3 | O165: =M165-N165 | P165: =IF(N165<>0,O165/N165,"") | W165: =SUM(R165:V165)-M165 | X165: =T165+U165+V165
B166: 东风鸿远工程咨询有限公司 | C166: 2121 | D166: E_628037 | E166: 襄阳市高新技术开发区一米森林园艺商行 | F166: 采购款 | G166: 供应商 | H166: CNY | M166: =J166+L166 | N166: -21636 | O166: =M166-N166 | P166: =IF(N166<>0,O166/N166,"") | W166: =SUM(R166:V166)-M166 | X166: =T166+U166+V166
B167: 东风鸿远工程咨询有限公司 | C167: 2121 | D167: E_601027 | E167: 上海志贺建筑设计事务所（普通合伙） | F167: 采购款 | G167: 供应商 | H167: CNY | M167: =J167+L167 | N167: -48500 | O167: =M167-N167 | P167: =IF(N167<>0,O167/N167,"") | W167: =SUM(R167:V167)-M167 | X167: =T167+U167+V167
B168: 东风鸿远工程咨询有限公司 | C168: 2121 | D168: E_032471 | E168: 罗蒙集团股份有限公司 | F168: 采购款 | G168: 供应商 | H168: CNY | M168: =J168+L168 | N168: -52290 | O168: =M168-N168 | P168: =IF(N168<>0,O168/N168,"") | W168: =SUM(R168:V168)-M168 | X168: =T168+U168+V168
B169: 东风鸿远工程咨询有限公司 | C169: 2121 | D169: E_617033 | E169: 襄阳市慢生活体育文化传媒有限公司 | F169: 采购款 | G169: 供应商 | H169: CNY | M169: =J169+L169 | N169: -73640 | O169: =M169-N169 | P169: =IF(N169<>0,O169/N169,"") | W169: =SUM(R169:V169)-M169 | X169: =T169+U169+V169
B170: 东风鸿远工程咨询有限公司 | C170: 2121 | D170: E_624943 | E170: 湖北筑美空间装饰设计有限公司 | F170: 采购款 | G170: 供应商 | H170: CNY | M170: =J170+L170 | N170: 0 | O170: =M170-N170 | P170: =IF(N170<>0,O170/N170,"") | W170: =SUM(R170:V170)-M170 | X170: =T170+U170+V170
B171: 东风鸿远工程咨询有限公司 | C171: 2121 | D171: E_155145 | E171: 武汉市勘察设计有限公司 | F171: 采购款 | G171: 供应商 | H171: CNY | M171: =J171+L171 | N171: -75471.7 | O171: =M171-N171 | P171: =IF(N171<>0,O171/N171,"") | W171: =SUM(R171:V171)-M171 | X171: =T171+U171+V171
B172: 东风鸿远工程咨询有限公司 | C172: 2121 | D172: E_624672 | E172: 湖北广怡基础建筑劳务有限公司 | F172: 采购款 | G172: 供应商 | H172: CNY | M172: =J172+L172 | N172: -430734.9 | O172: =M172-N172 | P172: =IF(N172<>0,O172/N172,"") | W172: =SUM(R172:V172)-M172 | X172: =T172+U172+V172
B173: 东风鸿远工程咨询有限公司 | C173: 2121 | D173: E_227520 | E173: 湖北科远环境检测有限公司 | F173: 采购款 | G173: 供应商 | H173: CNY | M173: =J173+L173 | N173: -340776.7 | O173: =M173-N173 | P173: =IF(N173<>0,O173/N173,"") | W173: =SUM(R173:V173)-M173 | X173: =T173+U173+V173
B174: 东风鸿远工程咨询有限公司 | C174: 2121 | D174: E_791242 | E174: 襄阳市高新区鑫永昌物流部 | F174: 采购款 | G174: 供应商 | H174: CNY | M174: =J174+L174 | N174: -15200 | O174: =M174-N174 | P174: =IF(N174<>0,O174/N174,"") | W174: =SUM(R174:V174)-M174 | X174: =T174+U174+V174
B175: 东风鸿远工程咨询有限公司 | C175: 2121 | D175: E_855078 | E175: 湖北星火合筑工程服务有限公司 | F175: 采购款 | G175: 供应商 | H175: CNY | M175: =J175+L175 | N175: -15533.99 | O175: =M175-N175 | P175: =IF(N175<>0,O175/N175,"") | W175: =SUM(R175:V175)-M175 | X175: =T175+U175+V175
B176: 东风鸿远工程咨询有限公司 | C176: 2121 | D176: E_146677 | E176: 湖北天洋机电工程有限公司 | F176: 采购款 | G176: 供应商 | H176: CNY | M176: =J176+L176 | N176: -82964.6 | O176: =M176-N176 | P176: =IF(N176<>0,O176/N176,"") | W176: =SUM(R176:V176)-M176 | X176: =T176+U176+V176
... B198: 东风鸿远工程咨询有限公司 | C198: 2121 | D198: E_620049 | E198: 上海清映数字科技有限公司 | F198: 采购款 | G198: 供应商 | H198: CNY | M198: =J198+L198 | N198: 0 | O198: =M198-N198 | P198: =IF(N198<>0,O198/N198,"") | W198: =SUM(R198:V198)-M198 | X198: =T198+U198+V198
B199: 东风鸿远工程咨询有限公司 | C199: 2121 | D199: E_626371 | E199: 深圳市景鸿建设工程有限公司 | F199: 采购款 | G199: 供应商 | H199: CNY | M199: =J199+L199 | N199: 0 | O199: =M199-N199 | P199: =IF(N199<>0,O199/N199,"") | Q199: NB4 | W199: =SUM(R199:V199)-M199 | X199: =T199+U199+V199
B200: 东风鸿远工程咨询有限公司 | C200: 2121 | D200: E_680313 | E200: 四川三问室内设计有限公司 | F200: 采购款 | G200: 供应商 | H200: CNY | M200: =J200+L200 | N200: -251622.77 | O200: =M200-N200 | P200: =IF(N200<>0,O200/N200,"") | W200: =SUM(R200:V200)-M200 | X200: =T200+U200+V200
B201: 东风鸿远工程咨询有限公司 | C201: 2121 | D201: E_600904 | E201: 上海邮电设计咨询研究院有限公司 | F201: 采购款 | G201: 供应商 | H201: CNY | M201: =J201+L201 | N201: -184905.66 | O201: =M201-N201 | P201: =IF(N201<>0,O201/N201,"") | W201: =SUM(R201:V201)-M201 | X201: =T201+U201+V201
B202: 东风鸿远工程咨询有限公司 | C202: 2121 | D202: E_014855 | E202: 湖北省工业建筑总承包集团 | F202: 采购款 | G202: 供应商 | H202: CNY | M202: =J202+L202 | N202: -1477909.1 | O202: =M202-N202 | P202: =IF(N202<>0,O202/N202,"") | Q202: NB5 | W202: =SUM(R202:V202)-M202 | X202: =T202+U202+V202
B203: 东风鸿远工程咨询有限公司 | C203: 2121 | D203: E_614399 | E203: 襄阳绘景园艺设计工程有限公司 | F203: 采购款 | G203: 供应商 | H203: CNY | M203: =J203+L203 | N203: -24466.02 | O203: =M203-N203 | P203: =IF(N203<>0,O203/N203,"") | W203: =SUM(R203:V203)-M203 | X203: =T203+U203+V203
B204: 东风鸿远工程咨询有限公司 | C204: 2121 | D204: E_586904 | E204: 上木(武汉)建筑设计有限公司 | F204: 采购款 | G204: 供应商 | H204: CNY | M204: =J204+L204 | N204: -69465.54 | O204: =M204-N204 | P204: =IF(N204<>0,O204/N204,"") | W204: =SUM(R204:V204)-M204 | X204: =T204+U204+V204
B205: 东风鸿远工程咨询有限公司 | C205: 2121 | D205: E_177460 | E205: 平安好医襄阳综合门诊部有限公司 | F205: 采购款 | G205: 供应商 | H205: CNY | M205: =J205+L205 | N205: -259750 | O205: =M205-N205 | P205: =IF(N205<>0,O205/N205,"") | W205: =SUM(R205:V205)-M205 | X205: =T205+U205+V205
B206: 东风鸿远工程咨询有限公司 | C206: 2121 | D206: E_619388 | E206: 保定岩墨工程勘察有限公司 | F206: 采购款 | G206: 供应商 | H206: CNY | M206: =J206+L206 | N206: 0 | O206: =M206-N206 | P206: =IF(N206<>0,O206/N206,"") | W206: =SUM(R206:V206)-M206 | X206: =T206+U206+V206
B207: 东风鸿远工程咨询有限公司 | C207: 2121 | D207: E_616717 | E207: 襄州区嘉泰建材商行 | F207: 采购款 | G207: 供应商 | H207: CNY | M207: =J207+L207 | N207: -46576.79 | O207: =M207-N207 | P207: =IF(N207<>0,O207/N207,"") | W207: =SUM(R207:V207)-M207 | X207: =T207+U207+V207
B208: 东风鸿远工程咨询有限公司 | C208: 2121 | D208: E_627817 | E208: 陕西明远城乡规划咨询有限公司 | F208: 采购款 | G208: 供应商 | H208: CNY | M208: =J208+L208 | N208: 0 | O208: =M208-N208 | P208: =IF(N208<>0,O208/N208,"") | W208: =SUM(R208:V208)-M208 | X208: =T208+U208+V208
B209: 东风鸿远工程咨询有限公司 | C209: 2121 | D209: E_614212 | E209: 襄阳路桥建设集团有限公司 | F209: 采购款 | G209: 供应商 | H209: CNY | M209: =J209+L209 | N209: -875055.51 | O209: =M209-N209 | P209: =IF(N209<>0,O209/N209,"") | W209: =SUM(R209:V209)-M209 | X209: =T209+U209+V209
B210: 东风鸿远工程咨询有限公司 | C210: 2121 | D210: E_843944 | E210: 武汉都市耕野建筑设计事务所（有限合伙） | F210: 采购款 | G210: 供应商 | H210: CNY | M210: =J210+L210 | N210: -52830.19 | O210: =M210-N210 | P210: =IF(N210<>0,O210/N210,"") | W210: =SUM(R210:V210)-M210 | X210: =T210+U210+V210
B211: 东风鸿远工程咨询有限公司 | C211: 2121 | D211: E_789222 | E211: 湖北水之清环保工程有限公司 | F211: 采购款 | G211: 供应商 | H211: CNY | M211: =J211+L211 | N211: -99873.79 | O211: =M211-N211 | P211: =IF(N211<>0,O211/N211,"") | W211: =SUM(R211:V211)-M211 | X211: =T211+U211+V211
B212: 东风鸿远工程咨询有限公司 | C212: 2121 | D212: E_689216 | E212: 南京优佳建筑设计有限公司湖北分公司 | F212: 采购款 | G212: 供应商 | H212: CNY | M212: =J212+L212 | N212: -56863.85 | O212: =M212-N212 | P212: =IF(N212<>0,O212/N212,"") | W212: =SUM(R212:V212)-M212 | X212: =T212+U212+V212
B213: 东风鸿远工程咨询有限公司 | C213: 2121 | D213: E_727626 | E213: 武汉融讯弘毅信息技术有限公司 | F213: 采购款 | G213: 供应商 | H213: CNY | M213: =J213+L213 | N213: -74943.4 | O213: =M213-N213 | P213: =IF(N213<>0,O213/N213,"") | W213: =SUM(R213:V213)-M213 | X213: =T213+U213+V213
B214: 东风鸿远工程咨询有限公司 | C214: 2121 | D214: E_604466 | E214: 华信咨询设计研究院有限公司 | F214: 采购款 | G214: 供应商 | H214: CNY | M214: =J214+L214 | N214: -126169.81 | O214: =M214-N214 | P214: =IF(N214<>0,O214/N214,"") | W214: =SUM(R214:V214)-M214 | X214: =T214+U214+V214
... B220: 东风鸿远工程咨询有限公司 | C220: 2121 | D220: E_006150 | E220: 湖北汽车工业学院 | F220: 采购款 | G220: 供应商 | H220: CNY | M220: =J220+L220 | N220: 0 | O220: =M220-N220 | P220: =IF(N220<>0,O220/N220,"") | W220: =SUM(R220:V220)-M220 | X220: =T220+U220+V220
H221: 合计 | I221: =SUM(I7:I220) | J221: =SUM(J7:J220) | K221: =SUM(K7:K220) | L221: =SUM(L7:L220) | M221: =SUM(M7:M220) | N221: =SUM(N7:N220) | O221: =SUM(O7:O220) | R221: =SUM(R7:R220) | S221: =SUM(S7:S220) | T221: =SUM(T7:T220) | U221: =SUM(U7:U220) | V221: =SUM(V7:V220) | W221: =SUM(W7:W220)
H222: check | J222: =J221-'N.00 Lead sheet'!F46 | M222: =M221-'N.00 Lead sheet'!J46 | N222: =N221-'N.00 Lead sheet'!K46
...

Sheet N.02 异常项复核
B1: 标准工作底稿: N SWP 应付账款
B2: N.02: 借方余额测试和异常项目复核
B4: 返回汇总页
B6: ='N.00 Lead sheet'!E15 | C6: 用于识别和测试项目的测试阈值
B8: 安永属性测试说明：
B9: 1）获取并检查支持异常项目/借方余额的文档（例如，供应商发票、合同、采购订单、付款水单等），以及与应付账款明细账的相关详细信息（例如，供应商名称、发票编号、发票金额和商品/服务的性质）核对一致。
B10: 2） 我们获取了与所选交易相关的记账分录。我们确认应付账款记账分录的对方科目账务处理正确‌。
B11: 3） 根据我们对支持性文件（包括记账分录）的审查，得出结论认为，所选交易在应付账款中的分类是适当的。
B13: 借方余额测试
B14: 表1 我们获取了N.01.01明细账BKD中期末余额为借方的供应商，对（单独或合计）大于测试阈值的借方余额，检查了对应的支持文件，确认是否需要进行重分类。
B16: 借项期末余额合计
B17: 是否执行借方余额测试 | C17: =IF(C16>'N.00 Lead sheet'!$E$15,"是","否")
B18: 是否调整 | C18: =IF(C16>'N.00 Lead sheet'!$C$6,"是","否")
B20: 分析所选项目，以进行了解和正确分类。
L22: EY Works
B23: 供应商名称 | C23: 借方余额 | D23: 形成应付账款借方余额入账凭证 | G23: 根据交易性质获取的支持性证据信息 | L23: 1 | M23: 2 | N23: 3 | O23: 备注
D24: 凭证编号 | E24: 日期 | F24: 金额 | G24: 交易性质 | H24: 交易凭据名称 | I24: 交易凭据编号 | J24: 交易凭据日期 | K24: 交易凭据金额
B34: 其他异常项测试
B36: 表2 在下面记录选择关键项目的理由
L41: EY Works
B42: 选择标准 | C42: 供应商名称 | D42: 应付账款入账凭证 | G42: 支持性证据信息 （确认控制权转移/接受服务的交易凭据，如提单、运输单据（GDN)、第三方交货证明等） | L42: 1 | M42: 2 | N42: 3 | O42: 备注
D43: 凭证编号 | E43: 日期 | F43: 金额 | G43: 交易性质 | H43: 交易凭据名称 | I43: 交易凭据编号 | J43: 交易凭据日期 | K43: 交易凭据金额
B50: Notes：记录识别的异常情况的详细信息以及如何解决这些异常情况，包括执行的额外实质性程序

Sheet N.03 截止测试
B1: 标准工作底稿: N SWP 应付账款
B2: N.03: 应付账款截止测试
B4: 返回汇总页
B6: 表1 记录确定测试期间和样本策略的理由。
B11: 表2 记录用于执行程序的总体
B13: 资料名称 | C13: 涵盖期间 | D13: 备注
B18: 测试：用于在正确期间正确评估交易记录的截止测试项目
B20: 安永属性测试说明：
B21: 根据支持性证据（例如，提单、运输单据（GDN)、第三方交货证明等）确定所选交易已记录在适当会计期间，包含所有关联的总账账户（如，资产负债表和利润表账户）中。
B23: 应付账款入账凭证 | F23: 支持性证据信息 （确认控制权转移/接受服务的交易凭据，如提单、运输单据（GDN)、第三方交货证明等） | I23: 金额涉及： （用“√”标记） | K23: EY Works | L23: 备注
B24: 凭证编号 | C24: 日期 | D24: 金额 | E24: 供应商名称 | F24: 交易凭据名称 | G24: 交易凭据编号 | H24: 交易发生日期 | I24: 本期 | J24: 资产负债表日后期间 | K24: 1
B25: 截止日前的交易测试
B36: 截止日后的交易测试
B48: Notes：记录识别的异常情况的详细信息以及如何解决这些异常情况，包括执行的额外实质性程序

Sheet N.04 寻找未入账负债
B1: 标准工作底稿: N SWP 应付账款
B2: N.04: 寻找未入账负债
B4: 返回汇总页
B6: 请项目组使用以下链接获取标准底稿执行Search For程序：
B7: N&P SURL SWP 寻找未入账负债 202YMMDD XYZ公司.xlsx

Sheet SkywindSettingSheet
A1: eca72055-06d3-4dd3-bf25-5248c0ca8d3d
