Workbook

Sheet 汇总
A1: V6 SWP
B2: 该科目涉及OSP底稿及函证底稿可参考此链接 | E2: Q1 SWP 利息资本化测试 202YMMDD XYZ公司.xlsx
B4: Q1.00 | C4: Q1.00 Lead（认定：E、C） | F4: 程序页 | G4: 执行 | H4: 不执行的原因 | I4: 注意事项
B5: 1 | C5: 通过执行分析和调查两期的长、短期借款科目重大变动来确定长、短期借款科目是否合理。 | F5: Q1.00 Lead
B6: Q1.01 | C6: Q1.01 Breakdown（认定：BS：E、V、C IS：O、M） | F6: 程序页 | G6: 执行 | H6: 不执行的原因 | I6: 注意事项
B7: 1 | C7: 获得借款和利息汇总表，并与总分类账余额核对一致。测试对期限、到期日的遵循情况。 | F7: Q1.01 BKD
B8: 2 | C8: 对借款的外币余额，我们使用第三方汇率(独立于被审计单位获得汇率)重新计算，并将重新计算的余额与被审计单位的余额进行比较。
B9: Q1.02 | C9: Q1.02 函证及抵质押担保测试（认定：E、V、C、R&O、P&D） | F9: 程序页 | G9: 执行 | H9: 不执行的原因 | I9: 注意事项
B10: 1 | C10: 我们对所有性质或金额重大的账户发送询证函，将回函金额核对至账面银行借款余额，并核对回函中的其他信息，我们在<Q.02a 函证>记录函证跟进工作； | F10: Q1.02a 函证
B11: 2 | C11: 对于期末的借款，询问管理层关于借款的担保情况，并检查回函及相关贷款协议的原始或授权副本或者其他相关文档等，测试并记录被审计单位是否遵守借款协议中约定的担保条款。 | F11: Q1.02b 抵押担保测试
A12: 096db42d-6ac9-49c1-8a94-f56a207d630a | B12: 3 | C12: 对未回函、未发函或回函信息不完整的借款余额，检查借款协议、银行回单等支持性证据，对其执行替代程序，验证借款的期限、利率、余额等是否与协议约定一致。 | F12: Q1.02c 函证-替代测试
B13: Q1.03 | C13: Q1.03 增加（ToD）（认定：E、V、R&O、P&D） | F13: 程序页 | G13: 执行 | H13: 不执行的原因 | I13: 注意事项
B14: 1 | C14: 对本期新签订的借款协议，执行详细测试，以验证记录的债务金额、利率、到期日、抵质押资产和担保人等条款的准确性及是否得到恰当的列报。 | F14: Q1.03 增加（ToD）
B15: Q1.04 | C15: Q1.04 利息费用（认定：C、R&O、P&D） | F15: 程序页 | G15: 执行 | H15: 不执行的原因 | I15: 注意事项
B16: 1 | C16: 执行实质性分析程序(SAP)测试利息费用，可参考264 GL 或Q1.04.SAP模板执行。如不执行，可直接执行利息测试TOD。 | F16: Q1.04 SAP | I16: PCAOB项目如采用实质性分析程序需要采用Form 264-SWP
B17: 2 | C17: 执行利息测试TOD，以获得关于利息费用的充分、适当的审计证据。 | F17: Q1.04.01 利息费用（ToD） | I17: 项目组对利息费用可根据实际情况采用SAP、TOD或重新计算的方法，三中方法任选其一，对利息费用执行审计程序
B18: 3 | C18: 对利息费用进行全量的测试，以获得关于利息费用的充分、适当的审计证据。 | F18: Q1.04.02 利息费用（重新计算）
B19: Q1.05 | C19: Q1.05 限制性契约（认定：C、R&O、P&D） | F19: 程序页 | G19: 执行 | H19: 不执行的原因 | I19: 注意事项
B20: 1 | C20: 对贷款合同中的契约或其他限制性条款执行实质性程序，以测试实体在整个期间是否遵守合同。 | F20: Q1.05 限制性契约

Sheet Q1.00 Lead
B1: 标准工作底稿：Q1 SWP 银行借款
B2: 客户名称 | D2: 此工作底稿需要与以下 Canvas PSP guided workflow forms一起使用： •Q1.00 Lead •Q1.01 Breakdown •Q1.02a 借款函证 •Q1.02b 抵押担保测试（如适用） •Q1.02c 函证-替代测试（如适用） •Q1.03 测试本年增加（如适用） •Q1.04 测试利息费用（如适用） •Q1.05 测试是否遵循贷款合同限制性契约（如适用） •Account conclusion （注：本底稿仅用于一般性银行借款测试）
B3: 期末 | C3: 46022
B4: 分析日期
B5: 可容忍误差(TE)
B6: 名义金额(SAD)
B7: 适用会计准则
B8: 记账本位币
B9: Q1.00 编制引导表并比较余额
B11: 返回汇总页
D13: Threshold(s) | K13: 安永标记
B14: 认定 | C14: CRA | D14: 各项认定1 | E14: 所有相关认定 2 | K14: TB | L14: 已与科目余额表核对无误
B15: 完整性（C） | D15: =IF(C15="Minimal",$C$5*50%,IF(C15="Low",$C$5*25%,IF(C15="Moderate",$C$5*15%,IF(C15="High",$C$5*10%,IF(C15="N/A","-",))))) -> 0 | E15: =MIN($D$15:$D$19) -> 0 | K15: PY | L15: 与上年最终审定数核对一致
B16: 存在性（E）/发生（O） | D16: =IF(C16="Minimal",$C$5*100%,IF(C16="Low",$C$5*75%,IF(C16="Moderate",$C$5*50%,IF(C16="High",$C$5*25%,IF(C16="N/A","-",))))) -> 0 | K16: A3 | L16: 与未审数、审定数核对一致
B17: 计量/计价（M/V） | D17: =IF(C17="Minimal",$C$5*100%,IF(C17="Low",$C$5*75%,IF(C17="Moderate",$C$5*50%,IF(C17="High",$C$5*25%,IF(C17="N/A","-",))))) -> 0 | K17: A5 | L17: 与审计调整核对一致
B18: 权利和义务（R&O） | D18: =IF(C18="Minimal",$C$5*100%,IF(C18="Low",$C$5*75%,IF(C18="Moderate",$C$5*50%,IF(C18="High",$C$5*25%,IF(C18="N/A","-",))))) -> 0 | K18: FS | L18: 与FS.0x与财务报表核对无误
B19: 列报和披露（P&D） | D19: =IF(C19="Minimal",$C$5*100%,IF(C19="Low",$C$5*75%,IF(C19="Moderate",$C$5*50%,IF(C19="High",$C$5*25%,IF(C19="N/A","-",))))) -> 0 | K19: w | L19: 低于SAD的金额——放弃进一步调查
B20: 1 各项认定的测试阈值，是根据EY GAM SUBSTANTIVE DESIGN 2.2.1 | K20: Rx | L20: 重新计算，无异常
B21: 中的示例测试阈值（用占TE的百分比表示）在相应风险等级（CRA）区间的上限计算得出的。 | K21: m | L21: 余额/活动不符合测试范围–无需进一步调查
B22: 除负债/费用类别账户的完整性认定应当使用负债/费用账户表之外，其他类别账户和认定均可使用资产/收入账户表。 | K22: SL | L22: 已与明细账核对无误
B23: 2.所有认定的阈值是使用所有相关认定中的最低阈值来计算的。我们在“引导表”标签页上将其用作：(a) 选择总账账户进行测试的起点，(b) 我们量化波动范围的金额。
B25: 在下文中描述我们当期对银行借款余额和相关波动的预期，以及这些预期的依据和理由。
B30: 波动范围
B31: ="波动幅度 ("&C8& "):" -> 波动幅度 (): | C31: =$E$15 -> 0
B32: 波动幅度（%）： | C32: 0.1
E36: |--------TB--------| | J36: |-------PY-------|
B37: 总账科目编码 | C37: 科目名称 | D37: 索引号 | E37: =C3 -> 46022 | J37: =DATE(YEAR($E$37)-1,12,31) -> 45657 | K37: 本期和上期期末余额 | M37: Notes | N37: 基于波动幅度判断，是否进一步调查？ | O37: 基于定性考虑判断，是否进一步调查？
E38: 期末账面数 | F38: 账表调整数 | G38: 期末未审数 | H38: 审计调整数 | I38: 期末审定数 | J38: 上期末审定数 | K38: 变动金额 | L38: 变动%
C39: 长期借款 | D39: Q1.01 BKD/ | G39: =E39+F39 -> 0 | I39: =G39+H39 -> 0 | K39: =E39-J39 -> 0 | L39: =IF(J39<>0,K39/J39,1) -> 1 | M39: [A] | N39: =IF(AND(ABS(K39)>=$C$31,ABS(L39)>=$C$32),"是","否") -> 是
C40: 短期借款 | G40: =E40+F40 -> 0 | I40: =G40+H40 -> 0 | K40: =E40-J40 -> 0 | L40: =IF(J40<>0,K40/J40,1) -> 1 | N40: =IF(AND(ABS(K40)>=$C$31,ABS(L40)>=$C$32),"是","否") -> 是
C41: 一年内到期的非流动负债 | G41: =E41+F41 -> 0 | I41: =G41+H41 -> 0 | K41: =E41-J41 -> 0 | L41: =IF(J41<>0,K41/J41,1) -> 1 | N41: =IF(AND(ABS(K41)>=$C$31,ABS(L41)>=$C$32),"是","否") -> 是
C42: 应付利息 | G42: =E42+F42 -> 0 | I42: =G42+H42 -> 0 | K42: =E42-J42 -> 0 | L42: =IF(J42<>0,K42/J42,1) -> 1 | N42: =IF(AND(ABS(K42)>=$C$31,ABS(L42)>=$C$32),"是","否") -> 是
D44: 合计 | E44: =SUM(E39:E43) -> 0 | F44: =SUM(F39:F43) -> 0 | G44: =SUM(G39:G43) -> 0 | H44: =SUM(H39:H43) -> 0 | I44: =SUM(I39:I43) -> 0 | J44: =SUM(J39:J43) -> 0 | K44: =E44-J44 -> 0 | L44: =IF(J44<>0,K44/J44,1) -> 1 | N44: =IF(AND(ABS(K44)>=$C$31,ABS(L44)>=$C$32),"是","否") -> 是
E45: Rx | F45: Rx | G45: Rx | H45: Rx | I45: Rx | J45: Rx
B47: 波动说明
B48: [A]
B52: 调整汇总表（如不适用请删除）
B53: 调整类型

Sheet Q1.01 BKD
B1: 标准工作底稿：Q1 SWP 银行借款
B2: Q1.01 银行借款明细与总账核对一致
B4: 返回汇总页
B6: =MIN('Q1.00 Lead'!E15) -> 0 | C6: 用于识别和测试调节项的测试阈值
B8: 表1 借款本金及利息Movement=>> | O8: 流动性分类、契约条件统计=>>
D9: |-------PY-------| | G9: TB/JE | H9: TB/JE
B10: 债务描述/债务工具 | C10: 总账账户 | D10: 期初余额 | E10: 本金增加/支取 | F10: 本金减免/偿还 | G10: 偿还的利息费用 | H10: 计提的利息费用 | I10: 重分类 | J10: 外币重新计量对记账本位币的影响 | K10: 期末余额 | L10: 试算表余额 | M10: 差额 | O10: 债务工具的流动部分 | P10: 债务工具的非流动部分 | Q10: 债务工具是否有契约条件？ （使用下拉列表） | R10: Notes1
B11: 借款1-本金 | K11: =D11+E11-F11+I11+J11 -> 0 | M11: =K11-L11 -> 0 | P11: =K11-O11 -> 0
B12: 借款2-本金 | K12: =D12+E12-F12+I12+J12 -> 0 | M12: =K12-L12 -> 0 | P12: =K12-O12 -> 0
B13: 借款利息-未到期的应计利息2 | K13: =D13+H13-G13+I13+J13 -> 0 | M13: =K13-L13 -> 0 | P13: =K13-O13 -> 0 | Q13: N/a
K14: =D14+H14-G14+I14+J14 -> 0 | M14: =K14-L14 -> 0 | P14: =K14-O14 -> 0
B15: 合计 | D15: =SUM(D11:D14) -> 0 | E15: =SUM(E11:E14) -> 0 | F15: =SUM(F11:F14) -> 0 | G15: =SUM(G11:G14) -> 0 | H15: =SUM(H11:H14) -> 0 | I15: =SUM(I11:I14) -> 0 | J15: =SUM(J11:J14) -> 0 | K15: =SUM(K11:K14) -> 0 | ... M15: =SUM(M11:M14) -> 0 | O15: =SUM(O11:O14) -> 0 | P15: =K15-O15 -> 0 | Q15: =COUNTIF(Q11:Q14,"是") -> 0
B16: 索引 | E16: Q.03 | H16: Q.04 | J16: Q.01表2 | K16: Q.02 | L16: Q.00 | Q16: Q.05
B18: 金额>针对所有认定的阈值 | E18: =IF(ABS(E15)>$B$6,"是","否") -> 否 | H18: =IF(ABS(H15)>$B$6,"是","否") -> 否 | J18: =IF(ABS(J15)>$B$6,"是","否") -> 否 | Q18: =IF(Q15=0,"否","是") -> 否
B20: 利息计提合理性检查3 | C20: =G15-D13+K13-H15 -> 0
B22: 1.如根据项目需要，为验证借款流动性分类是否正确、金融负债分类是否正确而额外执行了实质性程序，也请在此处做出索引
B23: 2.应计提而未到付息期的银行借款利息属于借款摊余成本的一部分，应当在本底稿中列示并测试，审计小组可以合并列示应计利息金额。
B24: 3.应对本年利息偿还与计提进行Tie in，当年偿还的利息费用-期初未到期应计利息+期末未到期应计利息+期末逾期利息（如有）=本年计提的利息费用，如有差异应当调查原因，并记录对差异执行的相关工作
B26: Notes
B32: 我们对外币借款的期末汇率重估进行了重新测算：
B34: 表2 外币相关程序
B35: 债务描述/债务工具 | C35: 原币币种 | D35: 原币期末金额 | E35: 期末汇率 | F35: 期末本币金额 | G35: 期末账面金额 | H35: 差额 | I35: Notes
B36: 借款1-本金 | F36: =D36*E36 -> 0 | G36: =K11 -> 0 | H36: =F36-G36 -> 0
B37: 借款2-本金 | F37: =D37*E37 -> 0 | H37: =F37-G37 -> 0
B38: 借款利息 | F38: =D38*E38 -> 0 | H38: =F38-G38 -> 0
B40: Notes 我们记录了所使用的资产负债表日汇率来源：[添加资产负债表日汇率公告]

Sheet Q1.02a 函证
B1: 标准工作底稿：Q1 SWP 银行借款
B2: Q1.02a 选择要进行函证的银行借款，编制并发送询证函，核对已函证余额，复核期限。
B4: 返回汇总页
B6: 需执行函证程序的债务工具。
B8: 安永属性测试说明：
B9: 1） 我们将函证中列报的金额与总账核对，确认了贷款或借款的未偿付余额。
B10: 2） 我们将贷款或借款的到期日与函证中所述日期进行比较，确认了贷款或借款的到期日在公司的时间表中准确体现。
B12: 债务工具
B13: 账面信息 | C13: 账面信息 | D13: 账面信息 | E13: 账面信息 | F13: 账面信息 | G13: 账面信息 | I13: 回函信息 | J13: 回函信息 | K13: 回函信息 | L13: 回函信息 | M13: 回函信息 | N13: 回函信息 | O13: 回函信息 | P13: 回函信息 | Q13: 回函信息 | R13: 差异跟进 | S13: 回函信息跟进 | T13: 回函信息跟进 | U13: 回函信息跟进 | V13: EY Works
B14: 公司名称/发函单位名称 | C14: 银行名称/资金借出方 | D14: 借款描述 | E14: 币种 | F14: 期末账面借款余额 （原币） A | G14: 期末账面借款余额 （本币） | H14: 函证编号 | I14: 公司名称/发函单位名称 | J14: 银行名称/资金借出方 | K14: 回函币种 | L14: 回函金额 B | M14: 借款日期 | N14: 到期日期 | O14: 利率 | P14: 抵（质）押品/担保人 | Q14: 备注 | R14: 回函金额差异 （原币） C=A-B | S14: 抵（质） 押品/担保测试底稿索引 | T14: 其他回函信息跟进工作底稿索引 | U14: 对未回函信息执行的替代测试索引1 | V14: 测试属性1 （相符，或记录差异跟进措施） | W14: 测试属性2 （相符，或记录差异跟进措施）
B25: 1.对于未回函或回函信息不完整的银行借款，我们应当在<Q.02c 函证-替代测试>中执行替代测试
F27: 45349

Sheet Q1.02b 抵押担保测试
B1: 标准工作底稿：Q1 SWP 银行借款
B2: Q1.02b 复核借款的期限、抵押品及其他担保限制情况
B4: 返回汇总页
B6: 需执行抵押担保测试的债务工具。
B8: 安永属性测试说明：
B9: 1） 我们复核了回函（包括对资产和负债的回函）及相关借款协议，查找以留置权、担保权益、衍生工具和抵押资产作为贷款抵押品的证据。我们将其交叉索引至相应的总账账户，并验证了相关披露。
B11: 债务工具
H12: 保证类条款 | K12: 抵质押情况 | R12: EY Works | S12: Notes
B13: 公司名称 | C13: 银行名称/资金借出方 | D13: 债务描述/债务工具 | E13: 函证编号 | F13: 总账余额 | G13: 已发生的债务违约及性质(如有) | H13: 保证合同索引号 | I13: 保证人 | J13: 保证金额 （仅适用于保证担保） | K13: 抵押/质押合同索引号 | L13: 抵（质）押物 | M13: 抵押资产权证号 （仅适用于不动产） | N13: 抵\质押\担保情况是否与回函核对一致 | O13: X_Ref - 抵质押品底稿 | P13: 质押/抵押资产账面净值 | Q13: 抵\质押资产所有权是否归属于被审计单位 | R13: 1
B23: 1 我们可以采用以下两种方法之一，来恰当记录我们对借款协议执行的审计工作：
B24: 1.1)我们将借款协议的关键条款doc或采用datasnipper的方式摘录至本工作底稿恰当的位置，并对相应的合同进行命名然后添加至canvas中；
B25: 1.2)我们在借款协议中对关键的条款进行标注或者Highlight，命名后上传至canvas，底稿中索引对应的借款合同。
B27: Notes
F33: 45471

Sheet Q1.02c 函证-替代测试
B1: 标准工作底稿：Q1 SWP 银行借款
B2: Q1.02c 对未回函/未发函的贷款和借款，执行替代程序
B4: 返回汇总页
B6: 执行替代程序（当未按预期收到回函或未发送函证时）：
B8: 安永属性测试说明：
B9: 1） 我们检查了贷款或借款未偿付余额的支持性文档记录，并将该金额与总账核对。
B10: 2） 我们将贷款或借款的到期日与协议中所述日期进行比较，验证了该贷款或借款的到期日准确反映在公司的时间表中。
B11: 3） 我们检查了作为贷款抵押品的留置权、担保权益、衍生工具和资产的支持性文档记录。我们交叉索引了相应的总账账户，并验证了相关披露。
B13: 债务工具 | E13: |-------Rx-------| | J13: EY Works
B14: 债务描述/债务工具 | C14: 根据支持性文档记录确定的金额 | D14: 总账余额 | E14: 支持性文档记录与总账金额之间的差额 | F14: 本金偿还期限 （即到期日） | G14: 利率 | H14: 限制条款 | I14: 已检查的凭据 | J14: 1 | K14: 2 | L14: 3 | M14: Notes
E15: =C15-D15 -> 0
E16: =C16-D16 -> 0
E17: =C17-D17 -> 0
E18: =C18-D18 -> 0
E19: =C19-D19 -> 0
D20: Q.00
B22: Notes
F28: 45471

Sheet Q1.03 增加（ToD）
B1: 标准工作底稿：Q1 SWP 银行借款
B2: Q1.03 详细测试（检查新协议）
B4: 返回汇总页
B6: 记录我们的详细测试所涵盖的样本总体（指引：进行充分描述，以使之前未参与审计的经验丰富的审计人员能够了解如何选择样本，如对总体进行分类和筛选）
B12: 借款协议本年增加总金额
B13: Breakdown中本年借款增加金额 | E13: ='Q1.01 BKD'!E15 -> 0 | F13: Q.01
B14: 差异 | E14: =E12-E13 -> 0 | F14: Rx | G14: 是否需要对差额进行进一步调查？ | J14: =IF(ABS(E14)>'Q1.00 Lead'!$C$6, "是", "否") -> 否
B16: 减：测试的关键项目 | E16: =SUM(K34:K40) -> 0
B17: 须进行代表性样本抽样的其余总体 | E17: =E12-E16 -> 0 | F17: Rx
B18: 1、如果选取的样本在以前年度已经执行过审计程序，且本年协议无变化，可将以前年度合同前推至本期，并在表1的备注列标注索引号。或者，将之前年度已检查并摘录的合同关键信息粘贴到本底稿，并在表1的备注列标注索引。
B20: 在下面描述选择关键项目的理由（请参阅Canvas引导式工作流程的“关键项目”部分，包括信息图标）
B25: 表1 我们对抽出的关键项和代表性样本执行以下程序：
B26: 安永属性测试说明：
B27: 对于每个选择测试的项目，我们检查了相关的第三方证据（如贷款协议），获取了管理层对贷款协议的评估，并执行了以下操作：
B28: 1）我们获取并检查了本年有新增/修改的借款协议，以验证借款金额、利率、到期日、转换权、币种、抵质押资产和担保人的准确性，从而得出结论，负债妥善记录于正确的期间内。
B29: 2）【如无此类条款，请标记N/a】我们检查了借款协议中有关赎回、其他提前还款特征和主观加速条款的相关章节，以确定负债在适当期间内准确记录。
B30: 3）【如无此类条款，请标记N/a】对于递延融资费用及相关摊销，我们评估了递延融资费用与对应借款的相关性。我们获得了被审计单位的递延融资费用计算结果，我们将计算结果与总账核对，并核对了计算过程，以验证计算的准确性，从而得出结论，这些递延融资融资费用妥善记入正确的期间。
B31: 4） 我们确定了将负债适当分类为非流动或流动贷款和借款是否符合协议条款和适用的财务报告框架。
L32: |-------Rx-------| | N32: EY Works
B33: 编号 | C33: 样本类型 （使用下拉列表） | D33: 债务描述/债务工具 | E33: 总账账户 | F33: 债权人 | G33: 协议签订日期 | H33: 到期日 | I33: 货币 | J33: 支持性文档记录中的本金金额 | K33: 总账中记录的金额 | L33: 支持性文档记录与总账金额之间的差额 | M33: 利率 | N33: 1 | O33: 2 | P33: 3 | Q33: 4 | R33: Notes
L34: =J34-K34 -> 0
L35: =J35-K35 -> 0
L36: =J36-K36 -> 0
L37: =J37-K37 -> 0
L38: =J38-K38 -> 0
L39: =J39-K39 -> 0
L40: =J40-K40 -> 0
B42: Notes
B47: 脚注
B48: 1.本工作底稿不涉及复杂安排的借款协议，如涉及转换权特征、赎回、其他提前还款特征和主观加速条款等嵌入特征，则需要制定其他实质性程序（OSP）来审计这些较复杂的安排，并在表1“备注”列中添加相关工作底稿索引。对于较复杂的安排，审计小组考虑在必要时邀请具有专业知识的专业人员参与； 2.如果贷款或借款为循环信贷额度，则本金金额为未偿付金额，而不是循环信贷额度的总额； 3.在评估债务流动性分类时，应考虑主观加速条款； 4.在该备注栏中，审计小组可添加交叉索引至会计备忘录，如金融负债或权益工具分类的测试。这些程序应当设计恰当的OSP来进行验证。
F59: 45471

Sheet Q1.04 SAP
B1: 标准工作底稿：Q1 SWP 银行借款
B2: Q1.04 实质性分析程序
B4: 返回汇总页
B6: 底稿索引： | C6: SAP模板可点击上方小灯泡获取

Sheet Q1.04.01 利息费用（ToD）
B1: 标准工作底稿：Q1 SWP 银行借款
B2: Q1.04.01 利息费用（ToD）
B4: 返回汇总页
B6: 记录我们的详细测试所涵盖的样本总体（指引：进行充分描述，以使之前未参与审计的经验丰富的审计人员能够了解如何选择样本，如对总体进行分类和筛选）
B12: 如涉及资本化利息测算可参考此链接： | D12: Q SWP 利息资本化测试 202YMMDD XYZ公司.xlsx
B14: 审计小组可根据实际情况，选择采取ToD抽样策略或全年重新计算策略进行利息金额的测试。
B15: 利息费用ToD测试
B17: 利息费用总体价值
B18: 根据后推表确定的金额 | D18: ='Q1.01 BKD'!H15 -> 0 | E18: Q.01
B19: 差额 | D19: =D17-D18 -> 0 | F19: 是否需要对差额进行进一步调查？ | H19: =IF(ABS(D19)>'Q1.00 Lead'!$C$6, "是", "否") -> 否
B21: 减：测试的关键项目 | D21: =SUMIF($C$40:$C$42,"关键项",$G$40:$G$42) -> 0
B22: 须进行代表性样本抽样的其余总体 | D22: =D17-D21 -> 0
B24: 在下面描述选择关键项目的理由：
B29: 安永属性测试说明：
B30: 1） 我们获取了实体的利息费用计算结果，并将计算结果与总账中记录的金额进行了核对。
B31: 2） 我们验证了利息费用计算的准确性。
B32: 3） 我们将利息费用明细表中使用的输入值追溯至源文档记录。
B33: 4） 我们参照适用的财务报告框架重新计算了利息费用计算中使用的实际利率，并重新计算了当期确定的利息费用。
B34: 5） 我们检查了第三方文档记录（例如，从交易对手处收到的银行对账单或函证），以支持并得出结论，以现金支付的利息记录于正确的期间，且金额正确。
B35: 6） 我们验证发现，以现金支付的利息符合贷款或借款协议的条款。
I38: |---------Rx---------| | L38: EY Works
B39: 编号 | C39: 样本类型 （使用下拉列表） | D39: 债务描述/债务工具 | E39: 总账账户 | F39: 交易对手方名称 | G39: 记录的利息费用 | H39: 支持性文档记录中的利息费用 | I39: 支持性文档记录与入账金额之间的差额 | J39: 利息确认日期 | K39: 备注 | L39: 1 | M39: 2 | N39: 3 | O39: 4 | P39: 5 | Q39: 6
I40: =G40-H40 -> 0
I41: =G41-H41 -> 0
I42: =G42-H42 -> 0
B44: 标记图例：记录识别的异常的详细信息以及如何解决这些异常，包括执行的额外实质性程序（指引:包括充分的描述，以使经验丰富目之前与审计没有关联的审计师能够了解执行的程序）

Sheet Q1.04.02 利息费用（重新计算）
B1: 标准工作底稿：Q1 SWP 银行借款
B2: Q1.04.02 利息费用（重新计算）
B4: 返回汇总页
B6: 审计小组可根据实际情况，选择采取ToD策略或全年重新计算策略进行利息金额的测试。
B7: 利息费用重新计算测试
B9: 如涉及资本化利息测算可参考此链接： | D9: Q1 SWP 利息资本化测试 202YMMDD XYZ公司.xlsx
B11: 安永属性测试说明：
B12: 1）我们获取了公司的利息费用计算表，并将计算表金额与总账中记录的金额进行了核对。
B13: 2）我们验证了利息费用计算表计算的准确性
B14: 3）我们将利息费用明细表中使用的数值追查至原始文档记录
B15: 4）我们根据适用的财务报告框架重新计算了利息费用计算中使用的实际利率，并重新计算了本期确认的利息费用。 （请自主设计计算表格并在本底稿中清楚记录计算过程及结果）
B17: 期初时间 | C17: 45658
B18: 期末时间 | C18: 46022
B20: 银行借款利息测算表
F21: |-------------------------------------------------------------------------------------------------------------------安永测试--------------------------------------- -- -----------------------------------------------------------------------|
B22: 总账账户 | C22: 债务描述/债务工具 | D22: 执行年利率 a | E22: 借款本金及变动 （借正贷负） b | F22: 借款本金变动时间 | G22: 单笔计息日 c | H22: 已发生利息合计 d=a*b*c/360 | I22: Notes | J22: 本年实际最后结息日 | K22: 本年实际最后结息日 至年末天数 e | L22: 应付利息余额测算 f=a*b(期末余额)*e/360 | M22: 应计利息（包括在借款余额中）g1 | N22: 尚未支付的到期利息（包括在应付利息中）g2 | O22: 测算差额 h=f-g1-g2
F23: =C17 -> 45658 | G23: =F24-F23 -> -45658 | H23: =-D23*E23*G23/360 -> 0 | K23: =IF(J23<>"",+$C$18-J23,0) -> 0 | L23: =D23*E23*K23/360 -> 0 | O23: =L23-M23-N23 -> 0
G24: =F25-F24 -> 0 | H24: =-D24*E24*G24/360 -> 0 | K24: =IF(J24<>"",+$C$18-J24,0) -> 0 | L24: =D24*E24*K24/360 -> 0 | O24: =L24-M24-N24 -> 0
G25: =F26-F25 -> 0 | H25: =-D25*E25*G25/360 -> 0 | K25: =IF(J25<>"",+$C$18-J25,0) -> 0 | L25: =D25*E25*K25/360 -> 0 | O25: =L25-M25-N25 -> 0
G26: =F27-F26 -> 0 | H26: =-D26*E26*G26/360 -> 0 | K26: =IF(J26<>"",+$C$18-J26,0) -> 0 | L26: =D26*E26*K26/360 -> 0 | O26: =L26-M26-N26 -> 0
G27: =F28-F27 -> 0 | H27: =-D27*E27*G27/360 -> 0 | K27: =IF(J27<>"",+$C$18-J27,0) -> 0 | L27: =D27*E27*K27/360 -> 0 | O27: =L27-M27-N27 -> 0
G28: =F29-F28 -> 0 | H28: =-D28*E28*G28/360 -> 0 | K28: =IF(J28<>"",+$C$18-J28,0) -> 0 | L28: =D28*E28*K28/360 -> 0 | O28: =L28-M28-N28 -> 0
G29: =F30-F29 -> 0 | H29: =-D29*E29*G29/360 -> 0 | K29: =IF(J29<>"",+$C$18-J29,0) -> 0 | L29: =D29*E29*K29/360 -> 0 | O29: =L29-M29-N29 -> 0
G30: =F31-F30 -> 0 | H30: =-D30*E30*G30/360 -> 0 | K30: =IF(J30<>"",+$C$18-J30,0) -> 0 | L30: =D30*E30*K30/360 -> 0 | O30: =L30-M30-N30 -> 0
H31: =-D31*E31*G31/360 -> 0 | K31: =IF(J31<>"",+$C$18-J31,0) -> 0 | L31: =D31*E31*K31/360 -> 0 | O31: =L31-M31-N31 -> 0
G32: 合计 | H32: =SUM(H23:H31) -> 0 | L32: =SUM(L23:L31) -> 0 | M32: =SUM(M23:M31) -> 0 | N32: =SUM(N23:N31) -> 0 | O32: =SUM(O23:O31) -> 0
H33: RX
B35: Uexp财务费用BKD | C35: 财务费用-利息支出
B36: J1.01BKD | C36: 在建工程-资本化利息
C37: [...]
C38: 合计 | D38: =SUM(D35:D37) -> 0
C39: 差异 | D39: =H32-D38 -> 0

Sheet Q1.05 限制性契约
B1: 标准工作底稿：Q1 SWP 银行借款
B2: Q1.05 测试遵循贷款协议契约条件的情况
B4: 返回汇总页
B6: 记录为识别我们合规测试所涵盖的债务工具而执行的程序：
B11: 具有限制性契约的借款数量
B12: Breakdown中的借款数量 | E12: ='Q1.01 BKD'!Q15 -> 0 | F12: Q.01
B13: 差额 | E13: =E11-E12 -> 0 | F13: Rx | G13: 是否需要对差额进行进一步调查？ | I13: =IF(ABS(E13)>'Q1.00 Lead'!$C$6, "是", "否") -> 否
B15: 减：本金已分类为流动负债的借款数量
B16: 测试总体 | E16: =E13-E15 -> 0
B18: 安永属性测试说明：
B19: 1） 我们获取了实体的契约条件合规情况文档记录和相关计算。
B20: 2） 我们将契约条件合规性计算的基础与已签署的债务协议核对一致。
B21: 3） 我们检查了相应的支持性文档记录（例如，经审计的试算表、财务报表或其他支持性证据），以支持契约条件合规性计算的输入值。
B22: 4） 我们验证了实体契约条件合规性计算的准确性。
B23: 5） 评估了财务报表中对限制性契约的披露是否符合适用的财务报告框架，以及是否对具有限制性契约的贷款安排产生的所有非流动负债进行了披露
J25: EY Works
B26: 编号 | C26: 债务描述/债务工具 | D26: 总账账户 | E26: 交易对手名称 | F26: 契约条件描述 | G26: 公司契约条件计算表明合规还是不合规？ （使用下拉列表） | H26: Notes | I26: 索引 | J26: 1 | K26: 2 | L26: 3 | M26: 4 | N26: 5
F27: 详见附注
F28: 详见附注
B30: 标记图例：记录识别的异常的详细信息以及如何解决这些异常，包括执行的额外实质性程序（指引:包括充分的描述，以使经验丰富目之前与审计没有关联的审计师能够了解执行的程序）
B35: 附注：针对编号1的贷款记录,我们摘录了<AA-01-3326 流动资金借款合同>. 并测试如下：
B37: 合同编号
B38: 借款金额
B39: 借款银行
B41: Step1 | C41: 摘录借款合同中的对被审计单位财务情况的限制条件：
B43: 条件1
B48: 测试过程
B51: 测试结论
B53: （如有其他条件，请继续添加）
B55: 结论
B57: （如适用）针对已经触发限制性条款的借款我们执行程序如下：
F59: 45471
